.DS_Store
ResBlaster/.DS_Store
ResBlaster/ResBlaster-NSConflict-hbucqp-mac12.4.py
ResBlaster/ResBlaster.py
ResBlaster/__init__-NSConflict-hbucqp-mac12.4.py
ResBlaster/__init__.py
ResBlaster/__pycache__/blaster.cpython-39.pyc
ResBlaster/db/.DS_Store
ResBlaster/db/ESBL.fsa
ResBlaster/db/bacmet1.fsa
ResBlaster/db/bacmet2_exp.fsa
ResBlaster/db/bacmet2_pred.fsa
ResBlaster/db/lmo.fsa
ResBlaster/db/ncbi.fsa
ResBlaster/db/resfinder-NSConflict-hbucqp-mac12.4.ndb
ResBlaster/db/resfinder-NSConflict-hbucqp-mac12.4.nin
ResBlaster/db/resfinder-NSConflict-hbucqp-mac12.4.ntf
ResBlaster/db/resfinder.fsa
ResBlaster/db/resfinder.ndb
ResBlaster/db/resfinder.nhr
ResBlaster/db/resfinder.nin
ResBlaster/db/resfinder.not
ResBlaster/db/resfinder.nsq
ResBlaster/db/resfinder.ntf
ResBlaster/db/resfinder.nto
ResBlaster/db/rpoB.fsa
ResBlaster/db/rpoB.ndb
ResBlaster/db/rpoB.nhr
ResBlaster/db/rpoB.nin
ResBlaster/db/rpoB.not
ResBlaster/db/rpoB.nsq
ResBlaster/db/rpoB.ntf
ResBlaster/db/rpoB.nto
ResBlaster/db/ssuis_vf.fsa
ResBlaster/db/vf_hps.fsa
ResBlaster/db/vfdb_core.fsa
ResBlaster/db/vfdb_full.fsa
ResBlaster-0.4.5.dist-info/METADATA
ResBlaster-0.4.5.dist-info/WHEEL
ResBlaster-0.4.5.dist-info/entry_points.txt
ResBlaster-0.4.5.dist-info/top_level.txt
ResBlaster-0.4.5.dist-info/RECORD
