Metadata-Version: 2.1
Name: ResBlaster
Version: 0.4.5
Summary: find antimcirobial resistance genes on genomes
Home-page: https://github.com/hbucqp/ResBlaster
Author: Qingpo Cui
Author-email: cqp@cau.edu.cn
License: MIT Licence
Keywords: pip,wgs,blastn,amr
Platform: any
Classifier: Development Status :: 3 - Alpha
Classifier: Intended Audience :: Developers
Classifier: Topic :: Software Development :: Build Tools
Classifier: License :: OSI Approved :: MIT License
Classifier: Programming Language :: Python :: 3
Classifier: Programming Language :: Python :: 3.6
Classifier: Programming Language :: Python :: 3.7
Classifier: Programming Language :: Python :: 3.8
Classifier: Programming Language :: Python :: 3.9
Classifier: Programming Language :: Python :: 3.10
Classifier: Programming Language :: Python :: 3.11
Requires-Dist: Bio
Requires-Dist: pandas
Requires-Dist: setuptools
Requires-Dist: cvmblaster (>=0.4.5)
Requires-Dist: cvmcore
Requires-Dist: tabulate
Requires-Dist: dask
